{
  "id": "74f69b46-a6f4-42ae-bc85-98e93ad4b866",
  "prevId": "00000000-0000-0000-0000-000000000000",
  "version": "7",
  "dialect": "postgresql",
  "tables": {
    "public.chapters": {
      "name": "chapters",
      "schema": "",
      "columns": {
        "id": {
          "name": "id",
          "type": "uuid",
          "primaryKey": true,
          "notNull": true,
          "default": "gen_random_uuid()"
        },
        "work_id": {
          "name": "work_id",
          "type": "uuid",
          "primaryKey": false,
          "notNull": true
        },
        "title": {
          "name": "title",
          "type": "varchar(255)",
          "primaryKey": false,
          "notNull": true
        },
        "content": {
          "name": "content",
          "type": "text",
          "primaryKey": false,
          "notNull": false
        },
        "order": {
          "name": "order",
          "type": "integer",
          "primaryKey": false,
          "notNull": true
        },
        "next_chapter_id": {
          "name": "next_chapter_id",
          "type": "uuid",
          "primaryKey": false,
          "notNull": false
        },
        "created_at": {
          "name": "created_at",
          "type": "timestamp",
          "primaryKey": false,
          "notNull": true,
          "default": "now()"
        },
        "updated_at": {
          "name": "updated_at",
          "type": "timestamp",
          "primaryKey": false,
          "notNull": true,
          "default": "now()"
        }
      },
      "indexes": {},
      "foreignKeys": {
        "chapters_work_id_works_id_fk": {
          "name": "chapters_work_id_works_id_fk",
          "tableFrom": "chapters",
          "tableTo": "works",
          "columnsFrom": [
            "work_id"
          ],
          "columnsTo": [
            "id"
          ],
          "onDelete": "cascade",
          "onUpdate": "no action"
        }
      },
      "compositePrimaryKeys": {},
      "uniqueConstraints": {},
      "policies": {},
      "checkConstraints": {},
      "isRLSEnabled": false
    },
    "public.character_relations": {
      "name": "character_relations",
      "schema": "",
      "columns": {
        "id": {
          "name": "id",
          "type": "uuid",
          "primaryKey": true,
          "notNull": true,
          "default": "gen_random_uuid()"
        },
        "work_id": {
          "name": "work_id",
          "type": "uuid",
          "primaryKey": false,
          "notNull": true
        },
        "character_id_a": {
          "name": "character_id_a",
          "type": "uuid",
          "primaryKey": false,
          "notNull": true
        },
        "character_id_b": {
          "name": "character_id_b",
          "type": "uuid",
          "primaryKey": false,
          "notNull": true
        },
        "relation_type": {
          "name": "relation_type",
          "type": "varchar(50)",
          "primaryKey": false,
          "notNull": true
        },
        "description": {
          "name": "description",
          "type": "text",
          "primaryKey": false,
          "notNull": false
        },
        "created_at": {
          "name": "created_at",
          "type": "timestamp",
          "primaryKey": false,
          "notNull": true,
          "default": "now()"
        },
        "updated_at": {
          "name": "updated_at",
          "type": "timestamp",
          "primaryKey": false,
          "notNull": true,
          "default": "now()"
        }
      },
      "indexes": {},
      "foreignKeys": {
        "character_relations_work_id_works_id_fk": {
          "name": "character_relations_work_id_works_id_fk",
          "tableFrom": "character_relations",
          "tableTo": "works",
          "columnsFrom": [
            "work_id"
          ],
          "columnsTo": [
            "id"
          ],
          "onDelete": "cascade",
          "onUpdate": "no action"
        },
        "character_relations_character_id_a_characters_id_fk": {
          "name": "character_relations_character_id_a_characters_id_fk",
          "tableFrom": "character_relations",
          "tableTo": "characters",
          "columnsFrom": [
            "character_id_a"
          ],
          "columnsTo": [
            "id"
          ],
          "onDelete": "cascade",
          "onUpdate": "no action"
        },
        "character_relations_character_id_b_characters_id_fk": {
          "name": "character_relations_character_id_b_characters_id_fk",
          "tableFrom": "character_relations",
          "tableTo": "characters",
          "columnsFrom": [
            "character_id_b"
          ],
          "columnsTo": [
            "id"
          ],
          "onDelete": "cascade",
          "onUpdate": "no action"
        }
      },
      "compositePrimaryKeys": {},
      "uniqueConstraints": {},
      "policies": {},
      "checkConstraints": {},
      "isRLSEnabled": false
    },
    "public.characters": {
      "name": "characters",
      "schema": "",
      "columns": {
        "id": {
          "name": "id",
          "type": "uuid",
          "primaryKey": true,
          "notNull": true,
          "default": "gen_random_uuid()"
        },
        "work_id": {
          "name": "work_id",
          "type": "uuid",
          "primaryKey": false,
          "notNull": true
        },
        "name": {
          "name": "name",
          "type": "varchar(255)",
          "primaryKey": false,
          "notNull": true
        },
        "avatar": {
          "name": "avatar",
          "type": "text",
          "primaryKey": false,
          "notNull": false
        },
        "background": {
          "name": "background",
          "type": "text",
          "primaryKey": false,
          "notNull": false
        },
        "personality": {
          "name": "personality",
          "type": "text",
          "primaryKey": false,
          "notNull": false
        },
        "goals": {
          "name": "goals",
          "type": "text",
          "primaryKey": false,
          "notNull": false
        },
        "attributes": {
          "name": "attributes",
          "type": "jsonb",
          "primaryKey": false,
          "notNull": false,
          "default": "'{}'::jsonb"
        },
        "created_at": {
          "name": "created_at",
          "type": "timestamp",
          "primaryKey": false,
          "notNull": true,
          "default": "now()"
        },
        "updated_at": {
          "name": "updated_at",
          "type": "timestamp",
          "primaryKey": false,
          "notNull": true,
          "default": "now()"
        }
      },
      "indexes": {},
      "foreignKeys": {
        "characters_work_id_works_id_fk": {
          "name": "characters_work_id_works_id_fk",
          "tableFrom": "characters",
          "tableTo": "works",
          "columnsFrom": [
            "work_id"
          ],
          "columnsTo": [
            "id"
          ],
          "onDelete": "cascade",
          "onUpdate": "no action"
        }
      },
      "compositePrimaryKeys": {},
      "uniqueConstraints": {},
      "policies": {},
      "checkConstraints": {},
      "isRLSEnabled": false
    },
    "public.event_characters": {
      "name": "event_characters",
      "schema": "",
      "columns": {
        "id": {
          "name": "id",
          "type": "uuid",
          "primaryKey": true,
          "notNull": true,
          "default": "gen_random_uuid()"
        },
        "event_id": {
          "name": "event_id",
          "type": "uuid",
          "primaryKey": false,
          "notNull": true
        },
        "character_id": {
          "name": "character_id",
          "type": "uuid",
          "primaryKey": false,
          "notNull": true
        },
        "role": {
          "name": "role",
          "type": "varchar(50)",
          "primaryKey": false,
          "notNull": false
        },
        "created_at": {
          "name": "created_at",
          "type": "timestamp",
          "primaryKey": false,
          "notNull": true,
          "default": "now()"
        }
      },
      "indexes": {},
      "foreignKeys": {
        "event_characters_event_id_events_id_fk": {
          "name": "event_characters_event_id_events_id_fk",
          "tableFrom": "event_characters",
          "tableTo": "events",
          "columnsFrom": [
            "event_id"
          ],
          "columnsTo": [
            "id"
          ],
          "onDelete": "cascade",
          "onUpdate": "no action"
        },
        "event_characters_character_id_characters_id_fk": {
          "name": "event_characters_character_id_characters_id_fk",
          "tableFrom": "event_characters",
          "tableTo": "characters",
          "columnsFrom": [
            "character_id"
          ],
          "columnsTo": [
            "id"
          ],
          "onDelete": "cascade",
          "onUpdate": "no action"
        }
      },
      "compositePrimaryKeys": {},
      "uniqueConstraints": {},
      "policies": {},
      "checkConstraints": {},
      "isRLSEnabled": false
    },
    "public.events": {
      "name": "events",
      "schema": "",
      "columns": {
        "id": {
          "name": "id",
          "type": "uuid",
          "primaryKey": true,
          "notNull": true,
          "default": "gen_random_uuid()"
        },
        "work_id": {
          "name": "work_id",
          "type": "uuid",
          "primaryKey": false,
          "notNull": true
        },
        "chapter_id": {
          "name": "chapter_id",
          "type": "uuid",
          "primaryKey": false,
          "notNull": false
        },
        "title": {
          "name": "title",
          "type": "varchar(255)",
          "primaryKey": false,
          "notNull": true
        },
        "description": {
          "name": "description",
          "type": "text",
          "primaryKey": false,
          "notNull": false
        },
        "time_point": {
          "name": "time_point",
          "type": "varchar(255)",
          "primaryKey": false,
          "notNull": false
        },
        "location": {
          "name": "location",
          "type": "varchar(255)",
          "primaryKey": false,
          "notNull": false
        },
        "cause_event_id": {
          "name": "cause_event_id",
          "type": "uuid",
          "primaryKey": false,
          "notNull": false
        },
        "effect_event_ids": {
          "name": "effect_event_ids",
          "type": "jsonb",
          "primaryKey": false,
          "notNull": false,
          "default": "'[]'::jsonb"
        },
        "created_at": {
          "name": "created_at",
          "type": "timestamp",
          "primaryKey": false,
          "notNull": true,
          "default": "now()"
        },
        "updated_at": {
          "name": "updated_at",
          "type": "timestamp",
          "primaryKey": false,
          "notNull": true,
          "default": "now()"
        }
      },
      "indexes": {},
      "foreignKeys": {
        "events_work_id_works_id_fk": {
          "name": "events_work_id_works_id_fk",
          "tableFrom": "events",
          "tableTo": "works",
          "columnsFrom": [
            "work_id"
          ],
          "columnsTo": [
            "id"
          ],
          "onDelete": "cascade",
          "onUpdate": "no action"
        },
        "events_chapter_id_chapters_id_fk": {
          "name": "events_chapter_id_chapters_id_fk",
          "tableFrom": "events",
          "tableTo": "chapters",
          "columnsFrom": [
            "chapter_id"
          ],
          "columnsTo": [
            "id"
          ],
          "onDelete": "no action",
          "onUpdate": "no action"
        }
      },
      "compositePrimaryKeys": {},
      "uniqueConstraints": {},
      "policies": {},
      "checkConstraints": {},
      "isRLSEnabled": false
    },
    "public.works": {
      "name": "works",
      "schema": "",
      "columns": {
        "id": {
          "name": "id",
          "type": "uuid",
          "primaryKey": true,
          "notNull": true,
          "default": "gen_random_uuid()"
        },
        "title": {
          "name": "title",
          "type": "varchar(255)",
          "primaryKey": false,
          "notNull": true
        },
        "description": {
          "name": "description",
          "type": "text",
          "primaryKey": false,
          "notNull": false
        },
        "cover_image": {
          "name": "cover_image",
          "type": "text",
          "primaryKey": false,
          "notNull": false
        },
        "created_at": {
          "name": "created_at",
          "type": "timestamp",
          "primaryKey": false,
          "notNull": true,
          "default": "now()"
        },
        "updated_at": {
          "name": "updated_at",
          "type": "timestamp",
          "primaryKey": false,
          "notNull": true,
          "default": "now()"
        }
      },
      "indexes": {},
      "foreignKeys": {},
      "compositePrimaryKeys": {},
      "uniqueConstraints": {},
      "policies": {},
      "checkConstraints": {},
      "isRLSEnabled": false
    },
    "public.world_settings": {
      "name": "world_settings",
      "schema": "",
      "columns": {
        "id": {
          "name": "id",
          "type": "uuid",
          "primaryKey": true,
          "notNull": true,
          "default": "gen_random_uuid()"
        },
        "work_id": {
          "name": "work_id",
          "type": "uuid",
          "primaryKey": false,
          "notNull": true
        },
        "category": {
          "name": "category",
          "type": "varchar(50)",
          "primaryKey": false,
          "notNull": true
        },
        "title": {
          "name": "title",
          "type": "varchar(255)",
          "primaryKey": false,
          "notNull": true
        },
        "content": {
          "name": "content",
          "type": "text",
          "primaryKey": false,
          "notNull": false
        },
        "created_at": {
          "name": "created_at",
          "type": "timestamp",
          "primaryKey": false,
          "notNull": true,
          "default": "now()"
        },
        "updated_at": {
          "name": "updated_at",
          "type": "timestamp",
          "primaryKey": false,
          "notNull": true,
          "default": "now()"
        }
      },
      "indexes": {},
      "foreignKeys": {
        "world_settings_work_id_works_id_fk": {
          "name": "world_settings_work_id_works_id_fk",
          "tableFrom": "world_settings",
          "tableTo": "works",
          "columnsFrom": [
            "work_id"
          ],
          "columnsTo": [
            "id"
          ],
          "onDelete": "cascade",
          "onUpdate": "no action"
        }
      },
      "compositePrimaryKeys": {},
      "uniqueConstraints": {},
      "policies": {},
      "checkConstraints": {},
      "isRLSEnabled": false
    }
  },
  "enums": {},
  "schemas": {},
  "sequences": {},
  "roles": {},
  "policies": {},
  "views": {},
  "_meta": {
    "columns": {},
    "schemas": {},
    "tables": {}
  }
}